{"match_id": 603464718, "barracks_status_dire": 48, "barracks_status_radiant": 63, "chat": [{"time": 3448, "type": "chat", "unit": "Fnatic.Fly", "key": "gg"}, {"time": 3450, "type": "chat", "unit": "Empire.VANSKOR <3 MeowMeow", "key": "gg"}, {"time": 3450, "type": "chat", "unit": "Empire.ALWAYSWANNAFLY", "key": "gg"}, {"time": 3450, "type": "chat", "unit": "Fnatic.N0tail", "key": "gg"}, {"time": 3451, "type": "chat", "unit": "Empire.Mag", "key": "GG"}, {"time": 3451, "type": "chat", "unit": "Empire.Resolut1on", "key": "ggwp"}, {"time": 3453, "type": "chat", "unit": "Fnatic.Era", "key": "gege"}], "cluster": 133, "cosmetics": {}, "dire_score": 0, "dire_team_id": 350190, "draft_timings": null, "duration": 2607, "engine": 0, "first_blood_time": 104, "game_mode": 2, "human_players": 10, "leagueid": 1014, "lobby_type": 1, "match_seq_num": 548795533, "negative_votes": 51, "objectives": [{"time": 955, "type": "CHAT_MESSAGE_FIRSTBLOOD", "slot": 7, "key": 0}, {"time": 1377, "type": "CHAT_MESSAGE_TOWER_KILL", "team": 3, "slot": 7}, {"time": 1616, "type": "CHAT_MESSAGE_TOWER_DENY", "team": 100, "slot": 2}, {"time": 1920, "type": "CHAT_MESSAGE_TOWER_KILL", "team": 2, "slot": 1}, {"time": 1930, "type": "CHAT_MESSAGE_ROSHAN_KILL", "team": 3}, {"time": 1930, "type": "CHAT_MESSAGE_AEGIS", "slot": 7}, {"time": 2138, "type": "CHAT_MESSAGE_TOWER_DENY", "team": 100, "slot": 7}, {"time": 2192, "type": "CHAT_MESSAGE_TOWER_KILL", "team": 3, "slot": 8}, {"time": 2232, "type": "CHAT_MESSAGE_TOWER_KILL", "team": 3, "slot": 7}, {"time": 2381, "type": "CHAT_MESSAGE_TOWER_DENY", "team": 100, "slot": 7}, {"time": 2594, "type": "CHAT_MESSAGE_ROSHAN_KILL", "team": 3}, {"time": 2596, "type": "CHAT_MESSAGE_AEGIS", "slot": 6}, {"time": 2663, "type": "CHAT_MESSAGE_TOWER_KILL", "team": 2, "slot": 2}, {"time": 2900, "type": "CHAT_MESSAGE_TOWER_KILL", "team": 2, "slot": 2}, {"time": 3190, "type": "CHAT_MESSAGE_TOWER_KILL", "team": 2, "slot": 0}, {"time": 3328, "type": "CHAT_MESSAGE_TOWER_KILL", "team": 2, "slot": 4}, {"time": 3337, "type": "CHAT_MESSAGE_BARRACKS_KILL", "key": "8"}, {"time": 3339, "type": "CHAT_MESSAGE_BARRACKS_KILL", "key": "4"}, {"time": 3376, "type": "CHAT_MESSAGE_ROSHAN_KILL", "team": 2}, {"time": 3377, "type": "CHAT_MESSAGE_AEGIS", "slot": 4}, {"time": 3443, "type": "CHAT_MESSAGE_TOWER_KILL", "team": 2, "slot": 1}, {"time": 3447, "type": "CHAT_MESSAGE_BARRACKS_KILL", "key": "32"}, {"time": 3450, "type": "CHAT_MESSAGE_BARRACKS_KILL", "key": "16"}], "picks_bans": [{"is_pick": false, "hero_id": 91, "team": 0, "order": 0, "ord": 0, "match_id": 603464718}, {"is_pick": false, "hero_id": 77, "team": 1, "order": 1, "ord": 1, "match_id": 603464718}, {"is_pick": false, "hero_id": 106, "team": 0, "order": 2, "ord": 2, "match_id": 603464718}, {"is_pick": false, "hero_id": 50, "team": 1, "order": 3, "ord": 3, "match_id": 603464718}, {"is_pick": true, "hero_id": 74, "team": 0, "order": 4, "ord": 4, "match_id": 603464718}, {"is_pick": true, "hero_id": 88, "team": 1, "order": 5, "ord": 5, "match_id": 603464718}, {"is_pick": true, "hero_id": 96, "team": 1, "order": 6, "ord": 6, "match_id": 603464718}, {"is_pick": true, "hero_id": 65, "team": 0, "order": 7, "ord": 7, "match_id": 603464718}, {"is_pick": false, "hero_id": 33, "team": 0, "order": 8, "ord": 8, "match_id": 603464718}, {"is_pick": false, "hero_id": 68, "team": 1, "order": 9, "ord": 9, "match_id": 603464718}, {"is_pick": false, "hero_id": 89, "team": 0, "order": 10, "ord": 10, "match_id": 603464718}, {"is_pick": false, "hero_id": 27, "team": 1, "order": 11, "ord": 11, "match_id": 603464718}, {"is_pick": true, "hero_id": 54, "team": 1, "order": 12, "ord": 12, "match_id": 603464718}, {"is_pick": true, "hero_id": 79, "team": 0, "order": 13, "ord": 13, "match_id": 603464718}, {"is_pick": true, "hero_id": 58, "team": 1, "order": 14, "ord": 14, "match_id": 603464718}, {"is_pick": true, "hero_id": 48, "team": 0, "order": 15, "ord": 15, "match_id": 603464718}, {"is_pick": false, "hero_id": 52, "team": 1, "order": 16, "ord": 16, "match_id": 603464718}, {"is_pick": false, "hero_id": 86, "team": 0, "order": 17, "ord": 17, "match_id": 603464718}, {"is_pick": true, "hero_id": 31, "team": 1, "order": 18, "ord": 18, "match_id": 603464718}, {"is_pick": true, "hero_id": 92, "team": 0, "order": 19, "ord": 19, "match_id": 603464718}], "positive_votes": 204, "radiant_gold_adv": [], "radiant_score": 0, "radiant_team_id": 46, "radiant_win": true, "radiant_xp_adv": [], "skill": null, "start_time": 1397141331, "teamfights": [], "tower_status_dire": 1792, "tower_status_radiant": 1846, "version": 20, "replay_salt": 1242512633, "series_id": 0, "series_type": 0, "league": {"leagueid": 1014, "ticket": null, "banner": null, "tier": "professional", "name": "\u4e16\u754c\u7535\u5b50\u7ade\u6280\u804c\u4e1a\u7cbe\u82f1\u8d5b WPC-DOTA2\u8054\u8d5b"}, "radiant_team": {"team_id": 46, "name": "Team Empire", "tag": "Empire", "logo_url": "https://steamcdn-a.akamaihd.net/apps/dota2/images/team_logos/46.png"}, "dire_team": {"team_id": 350190, "name": "Fnatic", "tag": "Fnatic", "logo_url": "https://steamcdn-a.akamaihd.net/apps/dota2/images/team_logos/350190.png"}, "players": [{"match_id": 603464718, "player_slot": 0, "ability_targets": null, "ability_upgrades_arr": null, "ability_uses": {}, "account_id": 86802844, "actions": {}, "additional_units": null, "assists": 17, "backpack_0": 0, "backpack_1": 0, "backpack_2": 0, "backpack_3": null, "buyback_log": [], "camps_stacked": 0, "connection_log": null, "creeps_stacked": 0, "damage": {}, "damage_inflictor": {}, "damage_inflictor_received": {}, "damage_taken": {}, "damage_targets": null, "deaths": 6, "denies": 2, "dn_t": [], "firstblood_claimed": null, "gold": null, "gold_per_min": 356, "gold_reasons": {}, "gold_spent": null, "gold_t": [], "hero_damage": null, "hero_healing": null, "hero_hits": {}, "hero_id": 65, "item_0": 102, "item_1": 41, "item_2": 48, "item_3": 1, "item_4": 116, "item_5": 30, "item_neutral": null, "item_uses": {}, "kill_streaks": {}, "killed": {}, "killed_by": {}, "kills": 2, "kills_log": [], "lane_pos": {}, "last_hits": 148, "leaver_status": 0, "level": 18, "lh_t": [], "life_state": {}, "max_hero_hit": {"value": 0}, "multi_kills": {}, "net_worth": null, "obs": {}, "obs_left_log": [], "obs_log": [], "obs_placed": 0, "party_id": null, "party_size": null, "performance_others": null, "permanent_buffs": null, "pred_vict": false, "purchase": {"dust": null}, "purchase_log": [], "randomed": false, "repicked": false, "roshans_killed": null, "rune_pickups": 0, "runes": {}, "runes_log": [], "sen": {}, "sen_left_log": [], "sen_log": [], "sen_placed": 0, "stuns": 0, "teamfight_participation": null, "times": [], "tower_damage": null, "towers_killed": null, "xp_per_min": 402, "xp_reasons": {}, "xp_t": [], "personaname": "Mag", "name": "Mag", "last_login": "2019-11-07T09:38:49.492Z", "radiant_win": true, "start_time": 1397141331, "duration": 2607, "cluster": 133, "lobby_type": 1, "game_mode": 2, "is_contributor": false, "patch": 10, "region": 3, "isRadiant": true, "win": 1, "lose": 0, "total_gold": 15468, "total_xp": 17466, "kills_per_min": 0.04602991944764096, "kda": 2, "abandons": 0, "neutral_kills": 0, "tower_kills": 0, "courier_kills": 0, "lane_kills": 0, "hero_kills": 0, "observer_kills": 0, "sentry_kills": 0, "roshan_kills": 0, "necronomicon_kills": 0, "ancient_kills": 0, "buyback_count": 0, "observer_uses": 0, "sentry_uses": 0, "is_roaming": false, "purchase_time": {}, "first_purchase_time": {}, "item_win": {}, "item_usage": {}, "actions_per_min": 0, "life_state_dead": 0, "rank_tier": 80, "cosmetics": [], "benchmarks": {"gold_per_min": {"raw": 356, "pct": 0.4016393442622951}, "xp_per_min": {"raw": 402, "pct": 0.20491803278688525}, "kills_per_min": {"raw": 0.04602991944764096, "pct": 0.13934426229508196}, "last_hits_per_min": {"raw": 3.406214039125431, "pct": 0.5245901639344263}, "hero_damage_per_min": {"raw": 0, "pct": 0}, "hero_healing_per_min": {"raw": 0, "pct": 0.7704918032786885}, "tower_damage": {}, "stuns_per_min": {"raw": 0, "pct": 0.01639344262295082}, "lhten": {}}}, {"match_id": 603464718, "player_slot": 1, "ability_targets": null, "ability_upgrades_arr": null, "ability_uses": null, "account_id": 86725175, "actions": null, "additional_units": null, "assists": 12, "backpack_0": 0, "backpack_1": 0, "backpack_2": 0, "backpack_3": null, "buyback_log": null, "camps_stacked": null, "connection_log": null, "creeps_stacked": null, "damage": null, "damage_inflictor": null, "damage_inflictor_received": null, "damage_taken": null, "damage_targets": null, "deaths": 12, "denies": 19, "dn_t": null, "firstblood_claimed": null, "gold": null, "gold_per_min": 493, "gold_reasons": null, "gold_spent": null, "gold_t": null, "hero_damage": null, "hero_healing": null, "hero_hits": null, "hero_id": 74, "item_0": 63, "item_1": 116, "item_2": 194, "item_3": 65, "item_4": 0, "item_5": 46, "item_neutral": null, "item_uses": null, "kill_streaks": null, "killed": null, "killed_by": null, "kills": 10, "kills_log": null, "lane_pos": null, "last_hits": 179, "leaver_status": 0, "level": 20, "lh_t": null, "life_state": null, "max_hero_hit": null, "multi_kills": null, "net_worth": null, "obs": null, "obs_left_log": null, "obs_log": null, "obs_placed": null, "party_id": null, "party_size": null, "performance_others": null, "permanent_buffs": null, "pings": null, "pred_vict": null, "purchase": null, "purchase_log": null, "randomed": null, "repicked": null, "roshans_killed": null, "rune_pickups": null, "runes": null, "runes_log": null, "sen": null, "sen_left_log": null, "sen_log": null, "sen_placed": null, "stuns": null, "teamfight_participation": null, "times": null, "tower_damage": null, "towers_killed": null, "xp_per_min": 504, "xp_reasons": null, "xp_t": null, "personaname": "1st", "name": "Resolut1on", "last_login": null, "radiant_win": true, "start_time": 1397141331, "duration": 2607, "cluster": 133, "lobby_type": 1, "game_mode": 2, "is_contributor": false, "patch": 10, "region": 3, "isRadiant": true, "win": 1, "lose": 0, "total_gold": 21420, "total_xp": 21898, "kills_per_min": 0.23014959723820483, "kda": 1, "abandons": 0, "rank_tier": 80, "cosmetics": [], "benchmarks": {"gold_per_min": {"raw": 493, "pct": 0.5163983303518187}, "xp_per_min": {"raw": 504, "pct": 0.23076923076923078}, "kills_per_min": {"raw": 0.23014959723820483, "pct": 0.6046511627906976}, "last_hits_per_min": {"raw": 4.119677790563866, "pct": 0.38640429338103754}, "hero_damage_per_min": {"raw": 0, "pct": 0}, "hero_healing_per_min": {"raw": 0, "pct": 0.8378056052474657}, "tower_damage": {}, "stuns_per_min": {"raw": 0, "pct": 0}, "lhten": {}}}, {"match_id": 603464718, "player_slot": 2, "ability_targets": null, "ability_upgrades_arr": null, "ability_uses": null, "account_id": 91064780, "actions": null, "additional_units": null, "assists": 18, "backpack_0": 0, "backpack_1": 0, "backpack_2": 0, "backpack_3": null, "buyback_log": null, "camps_stacked": null, "connection_log": null, "creeps_stacked": null, "damage": null, "damage_inflictor": null, "damage_inflictor_received": null, "damage_taken": null, "damage_targets": null, "deaths": 7, "denies": 4, "dn_t": null, "firstblood_claimed": null, "gold": null, "gold_per_min": 296, "gold_reasons": null, "gold_spent": null, "gold_t": null, "hero_damage": null, "hero_healing": null, "hero_hits": null, "hero_id": 92, "item_0": 37, "item_1": 166, "item_2": 108, "item_3": 36, "item_4": 214, "item_5": 30, "item_neutral": null, "item_uses": null, "kill_streaks": null, "killed": null, "killed_by": null, "kills": 2, "kills_log": null, "lane_pos": null, "last_hits": 69, "leaver_status": 0, "level": 16, "lh_t": null, "life_state": null, "max_hero_hit": null, "multi_kills": null, "net_worth": null, "obs": null, "obs_left_log": null, "obs_log": null, "obs_placed": null, "party_id": null, "party_size": null, "performance_others": null, "permanent_buffs": null, "pings": null, "pred_vict": null, "purchase": null, "purchase_log": null, "randomed": null, "repicked": null, "roshans_killed": null, "rune_pickups": null, "runes": null, "runes_log": null, "sen": null, "sen_left_log": null, "sen_log": null, "sen_placed": null, "stuns": null, "teamfight_participation": null, "times": null, "tower_damage": null, "towers_killed": null, "xp_per_min": 327, "xp_reasons": null, "xp_t": null, "personaname": "\u0441\u043b\u043e\u0432\u043e\u041f\u0410\u0426\u0410\u041d\u0410(\u043a\u0440\u044b\u0441\u0430)", "name": "ALWAYSWANNAFLY", "last_login": null, "radiant_win": true, "start_time": 1397141331, "duration": 2607, "cluster": 133, "lobby_type": 1, "game_mode": 2, "is_contributor": false, "patch": 10, "region": 3, "isRadiant": true, "win": 1, "lose": 0, "total_gold": 12861, "total_xp": 14208, "kills_per_min": 0.04602991944764096, "kda": 2, "abandons": 0, "rank_tier": 80, "cosmetics": [], "benchmarks": {"gold_per_min": {"raw": 296, "pct": 0.11976047904191617}, "xp_per_min": {"raw": 327, "pct": 0.0718562874251497}, "kills_per_min": {"raw": 0.04602991944764096, "pct": 0.023952095808383235}, "last_hits_per_min": {"raw": 1.5880322209436133, "pct": 0.1377245508982036}, "hero_damage_per_min": {"raw": 0, "pct": 0}, "hero_healing_per_min": {"raw": 0, "pct": 0.8023952095808383}, "tower_damage": {}, "stuns_per_min": {"raw": 0, "pct": 0.011976047904191617}, "lhten": {}}}, {"match_id": 603464718, "player_slot": 3, "ability_targets": null, "ability_upgrades_arr": null, "ability_uses": null, "account_id": 11550182, "actions": null, "additional_units": null, "assists": 12, "backpack_0": 0, "backpack_1": 0, "backpack_2": 0, "backpack_3": null, "buyback_log": null, "camps_stacked": null, "connection_log": null, "creeps_stacked": null, "damage": null, "damage_inflictor": null, "damage_inflictor_received": null, "damage_taken": null, "damage_targets": null, "deaths": 5, "denies": 3, "dn_t": null, "firstblood_claimed": null, "gold": null, "gold_per_min": 231, "gold_reasons": null, "gold_spent": null, "gold_t": null, "hero_damage": null, "hero_healing": null, "hero_hits": null, "hero_id": 79, "item_0": 63, "item_1": 92, "item_2": 102, "item_3": 46, "item_4": 0, "item_5": 34, "item_neutral": null, "item_uses": null, "kill_streaks": null, "killed": null, "killed_by": null, "kills": 4, "kills_log": null, "lane_pos": null, "last_hits": 21, "leaver_status": 0, "level": 15, "lh_t": null, "life_state": null, "max_hero_hit": null, "multi_kills": null, "net_worth": null, "obs": null, "obs_left_log": null, "obs_log": null, "obs_placed": null, "party_id": null, "party_size": null, "performance_others": null, "permanent_buffs": null, "pings": null, "pred_vict": null, "purchase": null, "purchase_log": null, "randomed": null, "repicked": null, "roshans_killed": null, "rune_pickups": null, "runes": null, "runes_log": null, "sen": null, "sen_left_log": null, "sen_log": null, "sen_placed": null, "stuns": null, "teamfight_participation": null, "times": null, "tower_damage": null, "towers_killed": null, "xp_per_min": 291, "xp_reasons": null, "xp_t": null, "personaname": "dattebayo", "name": "VANSKOR", "last_login": "2020-12-15T20:16:37.886Z", "radiant_win": true, "start_time": 1397141331, "duration": 2607, "cluster": 133, "lobby_type": 1, "game_mode": 2, "is_contributor": false, "patch": 10, "region": 3, "isRadiant": true, "win": 1, "lose": 0, "total_gold": 10036, "total_xp": 12643, "kills_per_min": 0.09205983889528192, "kda": 2, "abandons": 0, "rank_tier": 80, "cosmetics": [], "benchmarks": {"gold_per_min": {"raw": 231, "pct": 0.10256410256410256}, "xp_per_min": {"raw": 291, "pct": 0.11965811965811966}, "kills_per_min": {"raw": 0.09205983889528192, "pct": 0.3888888888888889}, "last_hits_per_min": {"raw": 0.48331415420023016, "pct": 0.029914529914529916}, "hero_damage_per_min": {"raw": 0, "pct": 0}, "hero_healing_per_min": {"raw": 0, "pct": 0.5256410256410257}, "tower_damage": {}, "stuns_per_min": {"raw": 0, "pct": 0}, "lhten": {}}}, {"match_id": 603464718, "player_slot": 4, "ability_targets": null, "ability_upgrades_arr": null, "ability_uses": null, "account_id": 89269794, "actions": null, "additional_units": null, "assists": 16, "backpack_0": 0, "backpack_1": 0, "backpack_2": 0, "backpack_3": null, "buyback_log": null, "camps_stacked": null, "connection_log": null, "creeps_stacked": null, "damage": null, "damage_inflictor": null, "damage_inflictor_received": null, "damage_taken": null, "damage_targets": null, "deaths": 2, "denies": 11, "dn_t": null, "firstblood_claimed": null, "gold": null, "gold_per_min": 576, "gold_reasons": null, "gold_spent": null, "gold_t": null, "hero_damage": null, "hero_healing": null, "hero_hits": null, "hero_id": 48, "item_0": 116, "item_1": 139, "item_2": 53, "item_3": 147, "item_4": 212, "item_5": 63, "item_neutral": null, "item_uses": null, "kill_streaks": null, "killed": null, "killed_by": null, "kills": 5, "kills_log": null, "lane_pos": null, "last_hits": 290, "leaver_status": 0, "level": 20, "lh_t": null, "life_state": null, "max_hero_hit": null, "multi_kills": null, "net_worth": null, "obs": null, "obs_left_log": null, "obs_log": null, "obs_placed": null, "party_id": null, "party_size": null, "performance_others": null, "permanent_buffs": null, "pings": null, "pred_vict": null, "purchase": null, "purchase_log": null, "randomed": null, "repicked": null, "roshans_killed": null, "rune_pickups": null, "runes": null, "runes_log": null, "sen": null, "sen_left_log": null, "sen_log": null, "sen_placed": null, "stuns": null, "teamfight_participation": null, "times": null, "tower_damage": null, "towers_killed": null, "xp_per_min": 490, "xp_reasons": null, "xp_t": null, "personaname": "\\/", "name": "Silent", "last_login": "2019-04-18T18:38:44.242Z", "radiant_win": true, "start_time": 1397141331, "duration": 2607, "cluster": 133, "lobby_type": 1, "game_mode": 2, "is_contributor": false, "patch": 10, "region": 3, "isRadiant": true, "win": 1, "lose": 0, "total_gold": 25027, "total_xp": 21290, "kills_per_min": 0.11507479861910241, "kda": 7, "abandons": 0, "rank_tier": null, "cosmetics": [], "benchmarks": {"gold_per_min": {"raw": 576, "pct": 0.4909478168264111}, "xp_per_min": {"raw": 490, "pct": 0.12779552715654952}, "kills_per_min": {"raw": 0.11507479861910241, "pct": 0.2417465388711395}, "last_hits_per_min": {"raw": 6.67433831990794, "pct": 0.34717784877529284}, "hero_damage_per_min": {"raw": 0, "pct": 0.0010649627263045794}, "hero_healing_per_min": {"raw": 0, "pct": 0.9020234291799787}, "tower_damage": {}, "stuns_per_min": {"raw": 0, "pct": 0.0010649627263045794}, "lhten": {}}}, {"match_id": 603464718, "player_slot": 128, "ability_targets": null, "ability_upgrades_arr": null, "ability_uses": null, "account_id": 94155156, "actions": null, "additional_units": null, "assists": 8, "backpack_0": 0, "backpack_1": 0, "backpack_2": 0, "backpack_3": null, "buyback_log": null, "camps_stacked": null, "connection_log": null, "creeps_stacked": null, "damage": null, "damage_inflictor": null, "damage_inflictor_received": null, "damage_taken": null, "damage_targets": null, "deaths": 6, "denies": 4, "dn_t": null, "firstblood_claimed": null, "gold": null, "gold_per_min": 258, "gold_reasons": null, "gold_spent": null, "gold_t": null, "hero_damage": null, "hero_healing": null, "hero_hits": null, "hero_id": 31, "item_0": 79, "item_1": 214, "item_2": 102, "item_3": 42, "item_4": 0, "item_5": 24, "item_neutral": null, "item_uses": null, "kill_streaks": null, "killed": null, "killed_by": null, "kills": 6, "kills_log": null, "lane_pos": null, "last_hits": 67, "leaver_status": 0, "level": 17, "lh_t": null, "life_state": null, "max_hero_hit": null, "multi_kills": null, "net_worth": null, "obs": null, "obs_left_log": null, "obs_log": null, "obs_placed": null, "party_id": null, "party_size": null, "performance_others": null, "permanent_buffs": null, "pings": null, "pred_vict": null, "purchase": null, "purchase_log": null, "randomed": null, "repicked": null, "roshans_killed": null, "rune_pickups": null, "runes": null, "runes_log": null, "sen": null, "sen_left_log": null, "sen_log": null, "sen_placed": null, "stuns": null, "teamfight_participation": null, "times": null, "tower_damage": null, "towers_killed": null, "xp_per_min": 358, "xp_reasons": null, "xp_t": null, "personaname": "T", "name": "Fly", "last_login": "2017-11-04T11:32:51.650Z", "radiant_win": true, "start_time": 1397141331, "duration": 2607, "cluster": 133, "lobby_type": 1, "game_mode": 2, "is_contributor": false, "patch": 10, "region": 3, "isRadiant": false, "win": 0, "lose": 1, "total_gold": 11210, "total_xp": 15555, "kills_per_min": 0.1380897583429229, "kda": 2, "abandons": 0, "rank_tier": 80, "cosmetics": [], "benchmarks": {"gold_per_min": {"raw": 258, "pct": 0.2424916573971079}, "xp_per_min": {"raw": 358, "pct": 0.24026696329254726}, "kills_per_min": {"raw": 0.1380897583429229, "pct": 0.6763070077864294}, "last_hits_per_min": {"raw": 1.5420023014959723, "pct": 0.7541713014460512}, "hero_damage_per_min": {"raw": 0, "pct": 0}, "hero_healing_per_min": {"raw": 0, "pct": 0.4671857619577308}, "tower_damage": {}, "stuns_per_min": {"raw": 0, "pct": 0.9098998887652948}, "lhten": {}}}, {"match_id": 603464718, "player_slot": 129, "ability_targets": null, "ability_upgrades_arr": null, "ability_uses": null, "account_id": 19672354, "actions": null, "additional_units": null, "assists": 6, "backpack_0": 0, "backpack_1": 0, "backpack_2": 0, "backpack_3": null, "buyback_log": null, "camps_stacked": null, "connection_log": null, "creeps_stacked": null, "damage": null, "damage_inflictor": null, "damage_inflictor_received": null, "damage_taken": null, "damage_targets": null, "deaths": 4, "denies": 0, "dn_t": null, "firstblood_claimed": null, "gold": null, "gold_per_min": 269, "gold_reasons": null, "gold_spent": null, "gold_t": null, "hero_damage": null, "hero_healing": null, "hero_hits": null, "hero_id": 58, "item_0": 41, "item_1": 180, "item_2": 108, "item_3": 36, "item_4": 187, "item_5": 46, "item_neutral": null, "item_uses": null, "kill_streaks": null, "killed": null, "killed_by": null, "kills": 3, "kills_log": null, "lane_pos": null, "last_hits": 84, "leaver_status": 0, "level": 15, "lh_t": null, "life_state": null, "max_hero_hit": null, "multi_kills": null, "net_worth": null, "obs": null, "obs_left_log": null, "obs_log": null, "obs_placed": null, "party_id": null, "party_size": null, "performance_others": null, "permanent_buffs": null, "pings": null, "pred_vict": null, "purchase": null, "purchase_log": null, "randomed": null, "repicked": null, "roshans_killed": null, "rune_pickups": null, "runes": null, "runes_log": null, "sen": null, "sen_left_log": null, "sen_log": null, "sen_placed": null, "stuns": null, "teamfight_participation": null, "times": null, "tower_damage": null, "towers_killed": null, "xp_per_min": 301, "xp_reasons": null, "xp_t": null, "personaname": "@(^_^)@", "name": "N0tail", "last_login": null, "radiant_win": true, "start_time": 1397141331, "duration": 2607, "cluster": 133, "lobby_type": 1, "game_mode": 2, "is_contributor": false, "patch": 10, "region": 3, "isRadiant": false, "win": 0, "lose": 1, "total_gold": 11688, "total_xp": 13078, "kills_per_min": 0.06904487917146145, "kda": 1, "abandons": 0, "rank_tier": 80, "cosmetics": [], "benchmarks": {"gold_per_min": {"raw": 269, "pct": 0.3201581027667984}, "xp_per_min": {"raw": 301, "pct": 0.13438735177865613}, "kills_per_min": {"raw": 0.06904487917146145, "pct": 0.3201581027667984}, "last_hits_per_min": {"raw": 1.9332566168009206, "pct": 0.5296442687747036}, "hero_damage_per_min": {"raw": 0, "pct": 0}, "hero_healing_per_min": {"raw": 0, "pct": 0.011857707509881422}, "tower_damage": {}, "stuns_per_min": {"raw": 0, "pct": 0.4031620553359684}, "lhten": {}}}, {"match_id": 603464718, "player_slot": 130, "ability_targets": null, "ability_upgrades_arr": null, "ability_uses": null, "account_id": 100317750, "actions": null, "additional_units": null, "assists": 7, "backpack_0": 0, "backpack_1": 0, "backpack_2": 0, "backpack_3": null, "buyback_log": null, "camps_stacked": null, "connection_log": null, "creeps_stacked": null, "damage": null, "damage_inflictor": null, "damage_inflictor_received": null, "damage_taken": null, "damage_targets": null, "deaths": 5, "denies": 27, "dn_t": null, "firstblood_claimed": null, "gold": null, "gold_per_min": 454, "gold_reasons": null, "gold_spent": null, "gold_t": null, "hero_damage": null, "hero_healing": null, "hero_hits": null, "hero_id": 54, "item_0": 50, "item_1": 154, "item_2": 151, "item_3": 185, "item_4": 9, "item_5": 143, "item_neutral": null, "item_uses": null, "kill_streaks": null, "killed": null, "killed_by": null, "kills": 12, "kills_log": null, "lane_pos": null, "last_hits": 177, "leaver_status": 0, "level": 20, "lh_t": null, "life_state": null, "max_hero_hit": null, "multi_kills": null, "net_worth": null, "obs": null, "obs_left_log": null, "obs_log": null, "obs_placed": null, "party_id": null, "party_size": null, "performance_others": null, "permanent_buffs": null, "pings": null, "pred_vict": null, "purchase": null, "purchase_log": null, "randomed": null, "repicked": null, "roshans_killed": null, "rune_pickups": null, "runes": null, "runes_log": null, "sen": null, "sen_left_log": null, "sen_log": null, "sen_placed": null, "stuns": null, "teamfight_participation": null, "times": null, "tower_damage": null, "towers_killed": null, "xp_per_min": 519, "xp_reasons": null, "xp_t": null, "personaname": "Jin", "name": "Era", "last_login": null, "radiant_win": true, "start_time": 1397141331, "duration": 2607, "cluster": 133, "lobby_type": 1, "game_mode": 2, "is_contributor": false, "patch": 10, "region": 3, "isRadiant": false, "win": 0, "lose": 1, "total_gold": 19726, "total_xp": 22550, "kills_per_min": 0.2761795166858458, "kda": 3, "abandons": 0, "rank_tier": 80, "cosmetics": [], "benchmarks": {"gold_per_min": {"raw": 454, "pct": 0.21962616822429906}, "xp_per_min": {"raw": 519, "pct": 0.14018691588785046}, "kills_per_min": {"raw": 0.2761795166858458, "pct": 0.7180685358255452}, "last_hits_per_min": {"raw": 4.073647871116226, "pct": 0.06230529595015576}, "hero_damage_per_min": {"raw": 0, "pct": 0.000778816199376947}, "hero_healing_per_min": {"raw": 0, "pct": 0.7515576323987538}, "tower_damage": {}, "stuns_per_min": {"raw": 0, "pct": 0.3613707165109034}, "lhten": {}}}, {"match_id": 603464718, "player_slot": 131, "ability_targets": null, "ability_upgrades_arr": null, "ability_uses": null, "account_id": 8712306, "actions": null, "additional_units": null, "assists": 5, "backpack_0": 0, "backpack_1": 0, "backpack_2": 0, "backpack_3": null, "buyback_log": null, "camps_stacked": null, "connection_log": null, "creeps_stacked": null, "damage": null, "damage_inflictor": null, "damage_inflictor_received": null, "damage_taken": null, "damage_targets": null, "deaths": 8, "denies": 7, "dn_t": null, "firstblood_claimed": null, "gold": null, "gold_per_min": 389, "gold_reasons": null, "gold_spent": null, "gold_t": null, "hero_damage": null, "hero_healing": null, "hero_hits": null, "hero_id": 96, "item_0": 90, "item_1": 214, "item_2": 46, "item_3": 1, "item_4": 114, "item_5": 0, "item_neutral": null, "item_uses": null, "kill_streaks": null, "killed": null, "killed_by": null, "kills": 5, "kills_log": null, "lane_pos": null, "last_hits": 218, "leaver_status": 0, "level": 18, "lh_t": null, "life_state": null, "max_hero_hit": null, "multi_kills": null, "net_worth": null, "obs": null, "obs_left_log": null, "obs_log": null, "obs_placed": null, "party_id": null, "party_size": null, "performance_others": null, "permanent_buffs": null, "pings": null, "pred_vict": null, "purchase": null, "purchase_log": null, "randomed": null, "repicked": null, "roshans_killed": null, "rune_pickups": null, "runes": null, "runes_log": null, "sen": null, "sen_left_log": null, "sen_log": null, "sen_placed": null, "stuns": null, "teamfight_participation": null, "times": null, "tower_damage": null, "towers_killed": null, "xp_per_min": 400, "xp_reasons": null, "xp_t": null, "personaname": "Kallu", "name": "Trixi", "last_login": null, "radiant_win": true, "start_time": 1397141331, "duration": 2607, "cluster": 133, "lobby_type": 1, "game_mode": 2, "is_contributor": false, "patch": 10, "region": 3, "isRadiant": false, "win": 0, "lose": 1, "total_gold": 16902, "total_xp": 17380, "kills_per_min": 0.11507479861910241, "kda": 1, "abandons": 0, "rank_tier": 80, "cosmetics": [], "benchmarks": {"gold_per_min": {"raw": 389, "pct": 0.27472527472527475}, "xp_per_min": {"raw": 400, "pct": 0.12637362637362637}, "kills_per_min": {"raw": 0.11507479861910241, "pct": 0.5082417582417582}, "last_hits_per_min": {"raw": 5.017261219792865, "pct": 0.49313186813186816}, "hero_damage_per_min": {"raw": 0, "pct": 0}, "hero_healing_per_min": {"raw": 0, "pct": 0.9271978021978022}, "tower_damage": {}, "stuns_per_min": {"raw": 0, "pct": 0}, "lhten": {}}}, {"match_id": 603464718, "player_slot": 132, "ability_targets": null, "ability_upgrades_arr": null, "ability_uses": null, "account_id": 21265941, "actions": null, "additional_units": null, "assists": 12, "backpack_0": 0, "backpack_1": 0, "backpack_2": 0, "backpack_3": null, "buyback_log": null, "camps_stacked": null, "connection_log": null, "creeps_stacked": null, "damage": null, "damage_inflictor": null, "damage_inflictor_received": null, "damage_taken": null, "damage_targets": null, "deaths": 3, "denies": 8, "dn_t": null, "firstblood_claimed": null, "gold": null, "gold_per_min": 299, "gold_reasons": null, "gold_spent": null, "gold_t": null, "hero_damage": null, "hero_healing": null, "hero_hits": null, "hero_id": 88, "item_0": 46, "item_1": 1, "item_2": 180, "item_3": 201, "item_4": 0, "item_5": 102, "item_neutral": null, "item_uses": null, "kill_streaks": null, "killed": null, "killed_by": null, "kills": 6, "kills_log": null, "lane_pos": null, "last_hits": 75, "leaver_status": 0, "level": 18, "lh_t": null, "life_state": null, "max_hero_hit": null, "multi_kills": null, "net_worth": null, "obs": null, "obs_left_log": null, "obs_log": null, "obs_placed": null, "party_id": null, "party_size": null, "performance_others": null, "permanent_buffs": null, "pings": null, "pred_vict": null, "purchase": null, "purchase_log": null, "randomed": null, "repicked": null, "roshans_killed": null, "rune_pickups": null, "runes": null, "runes_log": null, "sen": null, "sen_left_log": null, "sen_log": null, "sen_placed": null, "stuns": null, "teamfight_participation": null, "times": null, "tower_damage": null, "towers_killed": null, "xp_per_min": 420, "xp_reasons": null, "xp_t": null, "personaname": "H4nn1", "name": null, "last_login": null, "radiant_win": true, "start_time": 1397141331, "duration": 2607, "cluster": 133, "lobby_type": 1, "game_mode": 2, "is_contributor": false, "patch": 10, "region": 3, "isRadiant": false, "win": 0, "lose": 1, "total_gold": 12991, "total_xp": 18249, "kills_per_min": 0.1380897583429229, "kda": 4, "abandons": 0, "rank_tier": null, "cosmetics": [], "benchmarks": {"gold_per_min": {"raw": 299, "pct": 0.3911671924290221}, "xp_per_min": {"raw": 420, "pct": 0.2302839116719243}, "kills_per_min": {"raw": 0.1380897583429229, "pct": 0.6277602523659306}, "last_hits_per_min": {"raw": 1.7261219792865363, "pct": 0.6813880126182965}, "hero_damage_per_min": {"raw": 0, "pct": 0.0015772870662460567}, "hero_healing_per_min": {"raw": 0, "pct": 0.7334384858044164}, "tower_damage": {}, "stuns_per_min": {"raw": 0, "pct": 0.0015772870662460567}, "lhten": {}}}], "patch": 10, "region": 3, "all_word_counts": {"gg": 5, "ggwp": 1, "gege": 1}, "my_word_counts": {}, "throw": null, "loss": null, "replay_url": "http://replay133.valve.net/570/603464718_1242512633.dem.bz2"}